deta/__init__.py
deta/base.py
deta/drive.py
deta/service.py
deta/utils.py
deta/_async/__init__.py
deta/_async/client.py
deta-1.2.0.dist-info/LICENSE
deta-1.2.0.dist-info/METADATA
deta-1.2.0.dist-info/WHEEL
deta-1.2.0.dist-info/top_level.txt
deta-1.2.0.dist-info/RECORD
