Metadata-Version: 2.1
Name: deta
Version: 1.2.0
Summary: Python SDK for Deta Base & Deta Drive.
Home-page: http://github.com/deta/deta-python
Author: Deta
Author-email: hello@deta.sh
License: MIT
Platform: UNKNOWN
Classifier: Programming Language :: Python :: 3
Classifier: License :: OSI Approved :: MIT License
Classifier: Operating System :: OS Independent
Provides-Extra: async
